javac -g:none
Classfile /tmp/Class1.class
  Last modified Aug 6, 2020; size 322 bytes
  MD5 checksum 61696671496456d268ace78571210878
public class Class1
  minor version: 0
  major version: 52
  flags: ACC_PUBLIC, ACC_SUPER
Constant pool:
   #1 = Methodref          #6.#12         // java/lang/Object."<init>":()V
   #2 = Fieldref           #13.#14        // java/lang/System.out:Ljava/io/PrintStream;
   #3 = String             #15            // Class1
   #4 = Methodref          #16.#17        // java/io/PrintStream.println:(Ljava/lang/String;)V
   #5 = Class              #15            // Class1
   #6 = Class              #18            // java/lang/Object
   #7 = Utf8               <init>
   #8 = Utf8               ()V
   #9 = Utf8               Code
  #10 = Utf8               main
  #11 = Utf8               ([Ljava/lang/String;)V
  #12 = NameAndType        #7:#8          // "<init>":()V
  #13 = Class              #19            // java/lang/System
  #14 = NameAndType        #20:#21        // out:Ljava/io/PrintStream;
  #15 = Utf8               Class1
  #16 = Class              #22            // java/io/PrintStream
  #17 = NameAndType        #23:#24        // println:(Ljava/lang/String;)V
  #18 = Utf8               java/lang/Object
  #19 = Utf8               java/lang/System
  #20 = Utf8               out
  #21 = Utf8               Ljava/io/PrintStream;
  #22 = Utf8               java/io/PrintStream
  #23 = Utf8               println
  #24 = Utf8               (Ljava/lang/String;)V
{
  public Class1();
    descriptor: ()V
    flags: ACC_PUBLIC
    Code:
      stack=1, locals=1, args_size=1
         0: aload_0
         1: invokespecial #1                  // Method java/lang/Object."<init>":()V
         4: return

  public static void main(java.lang.String[]);
    descriptor: ([Ljava/lang/String;)V
    flags: ACC_PUBLIC, ACC_STATIC
    Code:
      stack=2, locals=1, args_size=1
         0: getstatic     #2                  // Field java/lang/System.out:Ljava/io/PrintStream;
         3: ldc           #3                  // String Class1
         5: invokevirtual #4                  // Method java/io/PrintStream.println:(Ljava/lang/String;)V
         8: return
}
