javac
[sudo] password for myname: 
Classfile /tmp/Class1.class
  Last modified Aug 6, 2020; size 403 bytes
  MD5 checksum b42e464b9aa8fdaaf28420a0275ccc1d
  Compiled from "Class1.java"
public class Class1
  minor version: 0
  major version: 52
  flags: ACC_PUBLIC, ACC_SUPER
Constant pool:
   #1 = Methodref          #6.#15         // java/lang/Object."<init>":()V
   #2 = Fieldref           #16.#17        // java/lang/System.out:Ljava/io/PrintStream;
   #3 = String             #18            // Class1
   #4 = Methodref          #19.#20        // java/io/PrintStream.println:(Ljava/lang/String;)V
   #5 = Class              #18            // Class1
   #6 = Class              #21            // java/lang/Object
   #7 = Utf8               <init>
   #8 = Utf8               ()V
   #9 = Utf8               Code
  #10 = Utf8               LineNumberTable
  #11 = Utf8               main
  #12 = Utf8               ([Ljava/lang/String;)V
  #13 = Utf8               SourceFile
  #14 = Utf8               Class1.java
  #15 = NameAndType        #7:#8          // "<init>":()V
  #16 = Class              #22            // java/lang/System
  #17 = NameAndType        #23:#24        // out:Ljava/io/PrintStream;
  #18 = Utf8               Class1
  #19 = Class              #25            // java/io/PrintStream
  #20 = NameAndType        #26:#27        // println:(Ljava/lang/String;)V
  #21 = Utf8               java/lang/Object
  #22 = Utf8               java/lang/System
  #23 = Utf8               out
  #24 = Utf8               Ljava/io/PrintStream;
  #25 = Utf8               java/io/PrintStream
  #26 = Utf8               println
  #27 = Utf8               (Ljava/lang/String;)V
{
  public Class1();
    descriptor: ()V
    flags: ACC_PUBLIC
    Code:
      stack=1, locals=1, args_size=1
         0: aload_0
         1: invokespecial #1                  // Method java/lang/Object."<init>":()V
         4: return
      LineNumberTable:
        line 1: 0

  public static void main(java.lang.String[]);
    descriptor: ([Ljava/lang/String;)V
    flags: ACC_PUBLIC, ACC_STATIC
    Code:
      stack=2, locals=1, args_size=1
         0: getstatic     #2                  // Field java/lang/System.out:Ljava/io/PrintStream;
         3: ldc           #3                  // String Class1
         5: invokevirtual #4                  // Method java/io/PrintStream.println:(Ljava/lang/String;)V
         8: return
      LineNumberTable:
        line 3: 0
        line 4: 8
}
SourceFile: "Class1.java"


----------------------------------
javac -parameters
Classfile /tmp/Class1.class
  Last modified Aug 6, 2020; size 440 bytes
  MD5 checksum 4ebb7c63fe71d67c8736e01b525f7204
  Compiled from "Class1.java"
public class Class1
  minor version: 0
  major version: 52
  flags: ACC_PUBLIC, ACC_SUPER
Constant pool:
   #1 = Methodref          #6.#17         // java/lang/Object."<init>":()V
   #2 = Fieldref           #18.#19        // java/lang/System.out:Ljava/io/PrintStream;
   #3 = String             #20            // Class1
   #4 = Methodref          #21.#22        // java/io/PrintStream.println:(Ljava/lang/String;)V
   #5 = Class              #20            // Class1
   #6 = Class              #23            // java/lang/Object
   #7 = Utf8               <init>
   #8 = Utf8               ()V
   #9 = Utf8               Code
  #10 = Utf8               LineNumberTable
  #11 = Utf8               main
  #12 = Utf8               ([Ljava/lang/String;)V
  #13 = Utf8               MethodParameters
  #14 = Utf8               args
  #15 = Utf8               SourceFile
  #16 = Utf8               Class1.java
  #17 = NameAndType        #7:#8          // "<init>":()V
  #18 = Class              #24            // java/lang/System
  #19 = NameAndType        #25:#26        // out:Ljava/io/PrintStream;
  #20 = Utf8               Class1
  #21 = Class              #27            // java/io/PrintStream
  #22 = NameAndType        #28:#29        // println:(Ljava/lang/String;)V
  #23 = Utf8               java/lang/Object
  #24 = Utf8               java/lang/System
  #25 = Utf8               out
  #26 = Utf8               Ljava/io/PrintStream;
  #27 = Utf8               java/io/PrintStream
  #28 = Utf8               println
  #29 = Utf8               (Ljava/lang/String;)V
{
  public Class1();
    descriptor: ()V
    flags: ACC_PUBLIC
    Code:
      stack=1, locals=1, args_size=1
         0: aload_0
         1: invokespecial #1                  // Method java/lang/Object."<init>":()V
         4: return
      LineNumberTable:
        line 1: 0

  public static void main(java.lang.String[]);
    descriptor: ([Ljava/lang/String;)V
    flags: ACC_PUBLIC, ACC_STATIC
    Code:
      stack=2, locals=1, args_size=1
         0: getstatic     #2                  // Field java/lang/System.out:Ljava/io/PrintStream;
         3: ldc           #3                  // String Class1
         5: invokevirtual #4                  // Method java/io/PrintStream.println:(Ljava/lang/String;)V
         8: return
      LineNumberTable:
        line 3: 0
        line 4: 8
    MethodParameters:
      Name                           Flags
      args
}
SourceFile: "Class1.java"


----------------------------------
javac -g
Classfile /tmp/Class1.class
  Last modified Aug 6, 2020; size 507 bytes
  MD5 checksum db61fd42540f7df3dfdf55606378ab86
  Compiled from "Class1.java"
public class Class1
  minor version: 0
  major version: 52
  flags: ACC_PUBLIC, ACC_SUPER
Constant pool:
   #1 = Methodref          #6.#20         // java/lang/Object."<init>":()V
   #2 = Fieldref           #21.#22        // java/lang/System.out:Ljava/io/PrintStream;
   #3 = String             #23            // Class1
   #4 = Methodref          #24.#25        // java/io/PrintStream.println:(Ljava/lang/String;)V
   #5 = Class              #23            // Class1
   #6 = Class              #26            // java/lang/Object
   #7 = Utf8               <init>
   #8 = Utf8               ()V
   #9 = Utf8               Code
  #10 = Utf8               LineNumberTable
  #11 = Utf8               LocalVariableTable
  #12 = Utf8               this
  #13 = Utf8               LClass1;
  #14 = Utf8               main
  #15 = Utf8               ([Ljava/lang/String;)V
  #16 = Utf8               args
  #17 = Utf8               [Ljava/lang/String;
  #18 = Utf8               SourceFile
  #19 = Utf8               Class1.java
  #20 = NameAndType        #7:#8          // "<init>":()V
  #21 = Class              #27            // java/lang/System
  #22 = NameAndType        #28:#29        // out:Ljava/io/PrintStream;
  #23 = Utf8               Class1
  #24 = Class              #30            // java/io/PrintStream
  #25 = NameAndType        #31:#32        // println:(Ljava/lang/String;)V
  #26 = Utf8               java/lang/Object
  #27 = Utf8               java/lang/System
  #28 = Utf8               out
  #29 = Utf8               Ljava/io/PrintStream;
  #30 = Utf8               java/io/PrintStream
  #31 = Utf8               println
  #32 = Utf8               (Ljava/lang/String;)V
{
  public Class1();
    descriptor: ()V
    flags: ACC_PUBLIC
    Code:
      stack=1, locals=1, args_size=1
         0: aload_0
         1: invokespecial #1                  // Method java/lang/Object."<init>":()V
         4: return
      LineNumberTable:
        line 1: 0
      LocalVariableTable:
        Start  Length  Slot  Name   Signature
            0       5     0  this   LClass1;

  public static void main(java.lang.String[]);
    descriptor: ([Ljava/lang/String;)V
    flags: ACC_PUBLIC, ACC_STATIC
    Code:
      stack=2, locals=1, args_size=1
         0: getstatic     #2                  // Field java/lang/System.out:Ljava/io/PrintStream;
         3: ldc           #3                  // String Class1
         5: invokevirtual #4                  // Method java/io/PrintStream.println:(Ljava/lang/String;)V
         8: return
      LineNumberTable:
        line 3: 0
        line 4: 8
      LocalVariableTable:
        Start  Length  Slot  Name   Signature
            0       9     0  args   [Ljava/lang/String;
}
SourceFile: "Class1.java"


----------------------------------
javac -g:none
Classfile /tmp/Class1.class
  Last modified Aug 6, 2020; size 322 bytes
  MD5 checksum 61696671496456d268ace78571210878
public class Class1
  minor version: 0
  major version: 52
  flags: ACC_PUBLIC, ACC_SUPER
Constant pool:
   #1 = Methodref          #6.#12         // java/lang/Object."<init>":()V
   #2 = Fieldref           #13.#14        // java/lang/System.out:Ljava/io/PrintStream;
   #3 = String             #15            // Class1
   #4 = Methodref          #16.#17        // java/io/PrintStream.println:(Ljava/lang/String;)V
   #5 = Class              #15            // Class1
   #6 = Class              #18            // java/lang/Object
   #7 = Utf8               <init>
   #8 = Utf8               ()V
   #9 = Utf8               Code
  #10 = Utf8               main
  #11 = Utf8               ([Ljava/lang/String;)V
  #12 = NameAndType        #7:#8          // "<init>":()V
  #13 = Class              #19            // java/lang/System
  #14 = NameAndType        #20:#21        // out:Ljava/io/PrintStream;
  #15 = Utf8               Class1
  #16 = Class              #22            // java/io/PrintStream
  #17 = NameAndType        #23:#24        // println:(Ljava/lang/String;)V
  #18 = Utf8               java/lang/Object
  #19 = Utf8               java/lang/System
  #20 = Utf8               out
  #21 = Utf8               Ljava/io/PrintStream;
  #22 = Utf8               java/io/PrintStream
  #23 = Utf8               println
  #24 = Utf8               (Ljava/lang/String;)V
{
  public Class1();
    descriptor: ()V
    flags: ACC_PUBLIC
    Code:
      stack=1, locals=1, args_size=1
         0: aload_0
         1: invokespecial #1                  // Method java/lang/Object."<init>":()V
         4: return

  public static void main(java.lang.String[]);
    descriptor: ([Ljava/lang/String;)V
    flags: ACC_PUBLIC, ACC_STATIC
    Code:
      stack=2, locals=1, args_size=1
         0: getstatic     #2                  // Field java/lang/System.out:Ljava/io/PrintStream;
         3: ldc           #3                  // String Class1
         5: invokevirtual #4                  // Method java/io/PrintStream.println:(Ljava/lang/String;)V
         8: return
}


----------------------------------
javac -g -parameters
Classfile /tmp/Class1.class
  Last modified Aug 6, 2020; size 537 bytes
  MD5 checksum 1df3761934c515d9f008bb4e2a311fd7
  Compiled from "Class1.java"
public class Class1
  minor version: 0
  major version: 52
  flags: ACC_PUBLIC, ACC_SUPER
Constant pool:
   #1 = Methodref          #6.#21         // java/lang/Object."<init>":()V
   #2 = Fieldref           #22.#23        // java/lang/System.out:Ljava/io/PrintStream;
   #3 = String             #24            // Class1
   #4 = Methodref          #25.#26        // java/io/PrintStream.println:(Ljava/lang/String;)V
   #5 = Class              #24            // Class1
   #6 = Class              #27            // java/lang/Object
   #7 = Utf8               <init>
   #8 = Utf8               ()V
   #9 = Utf8               Code
  #10 = Utf8               LineNumberTable
  #11 = Utf8               LocalVariableTable
  #12 = Utf8               this
  #13 = Utf8               LClass1;
  #14 = Utf8               main
  #15 = Utf8               ([Ljava/lang/String;)V
  #16 = Utf8               args
  #17 = Utf8               [Ljava/lang/String;
  #18 = Utf8               MethodParameters
  #19 = Utf8               SourceFile
  #20 = Utf8               Class1.java
  #21 = NameAndType        #7:#8          // "<init>":()V
  #22 = Class              #28            // java/lang/System
  #23 = NameAndType        #29:#30        // out:Ljava/io/PrintStream;
  #24 = Utf8               Class1
  #25 = Class              #31            // java/io/PrintStream
  #26 = NameAndType        #32:#33        // println:(Ljava/lang/String;)V
  #27 = Utf8               java/lang/Object
  #28 = Utf8               java/lang/System
  #29 = Utf8               out
  #30 = Utf8               Ljava/io/PrintStream;
  #31 = Utf8               java/io/PrintStream
  #32 = Utf8               println
  #33 = Utf8               (Ljava/lang/String;)V
{
  public Class1();
    descriptor: ()V
    flags: ACC_PUBLIC
    Code:
      stack=1, locals=1, args_size=1
         0: aload_0
         1: invokespecial #1                  // Method java/lang/Object."<init>":()V
         4: return
      LineNumberTable:
        line 1: 0
      LocalVariableTable:
        Start  Length  Slot  Name   Signature
            0       5     0  this   LClass1;

  public static void main(java.lang.String[]);
    descriptor: ([Ljava/lang/String;)V
    flags: ACC_PUBLIC, ACC_STATIC
    Code:
      stack=2, locals=1, args_size=1
         0: getstatic     #2                  // Field java/lang/System.out:Ljava/io/PrintStream;
         3: ldc           #3                  // String Class1
         5: invokevirtual #4                  // Method java/io/PrintStream.println:(Ljava/lang/String;)V
         8: return
      LineNumberTable:
        line 3: 0
        line 4: 8
      LocalVariableTable:
        Start  Length  Slot  Name   Signature
            0       9     0  args   [Ljava/lang/String;
    MethodParameters:
      Name                           Flags
      args
}
SourceFile: "Class1.java"
